streamlit_calendar_semver/__init__.py
streamlit_calendar_semver/frontend/.env
streamlit_calendar_semver/frontend/.prettierrc
streamlit_calendar_semver/frontend/build/asset-manifest.json
streamlit_calendar_semver/frontend/build/bootstrap.min.css
streamlit_calendar_semver/frontend/build/index.html
streamlit_calendar_semver/frontend/build/static/css/main.7ad33fdc.css
streamlit_calendar_semver/frontend/build/static/css/main.7ad33fdc.css.map
streamlit_calendar_semver/frontend/build/static/js/main.beb4af9b.js
streamlit_calendar_semver/frontend/build/static/js/main.beb4af9b.js.LICENSE.txt
streamlit_calendar_semver/frontend/build/static/js/main.beb4af9b.js.map
streamlit_calendar_semver/frontend/package-lock.json
streamlit_calendar_semver/frontend/package.json
streamlit_calendar_semver/frontend/public/bootstrap.min.css
streamlit_calendar_semver/frontend/public/index.html
streamlit_calendar_semver/frontend/src/Calendar.css
streamlit_calendar_semver/frontend/src/Calendar.tsx
streamlit_calendar_semver/frontend/src/index.tsx
streamlit_calendar_semver/frontend/src/react-app-env.d.ts
streamlit_calendar_semver/frontend/tsconfig.json
streamlit_calendar_semver-0.5.0.dist-info/LICENSE
streamlit_calendar_semver-0.5.0.dist-info/METADATA
streamlit_calendar_semver-0.5.0.dist-info/WHEEL
streamlit_calendar_semver-0.5.0.dist-info/RECORD
