Metadata-Version: 2.1
Name: streamlit-calendar-semver
Version: 0.5.0
Summary: 📆 A Streamlit component to show callendar using FullCalendar (https://fullcalendar.io)
Home-page: https://github.com/im-perativa/streamlit-calendar-semver
License: Apache-2.0
Keywords: streamlit,streamlit-component
Author: Muhammad Luqman
Author-email: im.imperativa@gmail.com
Requires-Python: >=3.8,<4.0
Classifier: License :: OSI Approved :: Apache Software License
Classifier: Programming Language :: Python :: 3
Classifier: Programming Language :: Python :: 3.8
Classifier: Programming Language :: Python :: 3.9
Classifier: Programming Language :: Python :: 3.10
Classifier: Programming Language :: Python :: 3.11
Requires-Dist: streamlit (>=1.12.0,<2.0.0)
Project-URL: Repository, https://github.com/im-perativa/streamlit-calendar-semver
